{
  "attributes": [
    {
      "allow_nil?": false,
      "default": "fragment(\"uuid_generate_v7()\")",
      "generated?": false,
      "precision": null,
      "primary_key?": true,
      "references": null,
      "scale": null,
      "size": null,
      "source": "id",
      "type": "uuid"
    },
    {
      "allow_nil?": true,
      "default": "nil",
      "generated?": false,
      "precision": null,
      "primary_key?": false,
      "references": {
        "deferrable": false,
        "destination_attribute": "id",
        "destination_attribute_default": null,
        "destination_attribute_generated": null,
        "index?": false,
        "match_type": null,
        "match_with": null,
        "multitenancy": {
          "attribute": null,
          "global": null,
          "strategy": null
        },
        "name": "games_villian_id_fkey",
        "on_delete": null,
        "on_update": null,
        "primary_key?": true,
        "schema": "public",
        "table": "cards"
      },
      "scale": null,
      "size": null,
      "source": "villian_id",
      "type": "uuid"
    },
    {
      "allow_nil?": true,
      "default": "nil",
      "generated?": false,
      "precision": null,
      "primary_key?": false,
      "references": {
        "deferrable": false,
        "destination_attribute": "id",
        "destination_attribute_default": null,
        "destination_attribute_generated": null,
        "index?": false,
        "match_type": null,
        "match_with": null,
        "multitenancy": {
          "attribute": null,
          "global": null,
          "strategy": null
        },
        "name": "games_main_scheme_id_fkey",
        "on_delete": null,
        "on_update": null,
        "primary_key?": true,
        "schema": "public",
        "table": "cards"
      },
      "scale": null,
      "size": null,
      "source": "main_scheme_id",
      "type": "uuid"
    }
  ],
  "base_filter": null,
  "check_constraints": [],
  "custom_indexes": [],
  "custom_statements": [],
  "has_create_action": true,
  "hash": "E16B19FAC0E6231EC80FF7E4C16039CB496C24C621AE13B37AB7AC85CB929777",
  "identities": [],
  "multitenancy": {
    "attribute": null,
    "global": null,
    "strategy": null
  },
  "repo": "Elixir.Sanctum.Repo",
  "schema": null,
  "table": "games"
}